drift/VERSION
drift/__init__.py
drift/devapp.py
drift/fixers.py
drift/flaskfactory.py
drift/orm.py
drift/systesthelper.py
drift/urlregistry.py
drift/utils.py
drift/uwsgiboot.py
drift/version.py
drift/webservers.py
drift/contrib/__init__.py
drift/contrib/alembic.py
drift/contrib/apps/__init__.py
drift/contrib/apps/servicestatus/__init__.py
drift/contrib/apps/servicestatus/static/templates/index.html
drift/contrib/aws/__init__.py
drift/contrib/aws/lambdawsgi.py
drift/contrib/extensions/__init__.py
drift/contrib/flask/__init__.py
drift/contrib/flask/datadogapp.py
drift/contrib/flask/devapp.py
drift/contrib/flask/plainapp.py
drift/core/__init__.py
drift/core/apps/__init__.py
drift/core/apps/healthcheck.py
drift/core/apps/provision.py
drift/core/apps/schemas.py
drift/core/extensions/__init__.py
drift/core/extensions/apierrors.py
drift/core/extensions/apikeyrules.py
drift/core/extensions/debughelpers.py
drift/core/extensions/driftconfig.py
drift/core/extensions/httpmethod.py
drift/core/extensions/jwt.py
drift/core/extensions/logging.py
drift/core/extensions/messagebus.py
drift/core/extensions/schemachecker.py
drift/core/extensions/tenancy.py
drift/core/extensions/tracking.py
drift/core/extensions/urlregistry.py
drift/core/extensions/tests/__init__.py
drift/core/extensions/tests/test_apikeyrules.py
drift/core/resources/__init__.py
drift/core/resources/apitarget.py
drift/core/resources/awsdeploy.py
drift/core/resources/jwtsession.py
drift/core/resources/postgres.py
drift/core/resources/redis.py
drift/core/resources/sentry.py
drift/management/__init__.py
drift/management/gittools.py
drift/management/commands/__init__.py
drift/management/commands/ami.py
drift/management/commands/logs.py
drift/management/commands/quickdeploy.py
drift/management/commands/remotecmd.py
drift/management/commands/ssh.py
drift/tests/__init__.py
drift/tests/test_httpmethod.py
drift/tests/test_porting.py
drift/tests/test_soakit.py
python_drift-0.6.3.data/scripts/drift-admin.py
python_drift-0.6.3.dist-info/LICENSE
python_drift-0.6.3.dist-info/METADATA
python_drift-0.6.3.dist-info/WHEEL
python_drift-0.6.3.dist-info/entry_points.txt
python_drift-0.6.3.dist-info/top_level.txt
python_drift-0.6.3.dist-info/RECORD
